pesto/__init__.py
pesto/config.py
pesto/core.py
pesto/data.py
pesto/loader.py
pesto/main.py
pesto/model.py
pesto/utils/__init__.py
pesto/utils/cached_conv.py
pesto/utils/crop_cqt.py
pesto/utils/export.py
pesto/utils/hcqt.py
pesto/utils/parser.py
pesto/utils/reduce_activations.py
pesto/weights/mir-1k.ckpt
pesto/weights/mir-1k_g7.ckpt
pesto_pitch-2.0.0.dist-info/LICENSE.md
pesto_pitch-2.0.0.dist-info/METADATA
pesto_pitch-2.0.0.dist-info/WHEEL
pesto_pitch-2.0.0.dist-info/entry_points.txt
pesto_pitch-2.0.0.dist-info/top_level.txt
pesto_pitch-2.0.0.dist-info/RECORD
