Metadata-Version: 2.2
Name: pesto-pitch
Version: 2.0.0
Summary: Efficient pitch estimation with self-supervised learning
Author-email: Alain Riou <alain.riou@sony.com>
Project-URL: source, https://github.com/SonyCSLParis/pesto
Classifier: Development Status :: 4 - Beta
Classifier: Intended Audience :: Developers
Classifier: License :: OSI Approved :: GNU Lesser General Public License v3 (LGPLv3)
Classifier: Programming Language :: Python :: 3.8
Classifier: Programming Language :: Python :: 3.9
Classifier: Programming Language :: Python :: 3.10
Classifier: Programming Language :: Python :: 3.11
Requires-Python: >=3.8
License-File: LICENSE.md
Requires-Dist: numpy>=1.21.5
Requires-Dist: omegaconf>=2.3.0
Requires-Dist: scipy>=1.8.1
Requires-Dist: tqdm>=4.66.1
Requires-Dist: torch>=2.0.1
Requires-Dist: torchaudio>=2.0.2
Provides-Extra: matplotlib
Requires-Dist: matplotlib; extra == "matplotlib"
Provides-Extra: test
Requires-Dist: pytest; extra == "test"
